[
    {
        "comment": "得出结论:\n1.我们需要被爱\n2.不要过度在意别人对自己的看法\n3.尝试换一种角度看生活,不要总是沉迷于痛苦当中",
        "user_name": "sodja-_",
        "user_sex": "男",
        "like_count": 15,
        "reply_count": 0,
        "comment_date": "2022-07-30 14:55:37",
        "confidence": 0,
        "positive": 0,
        "negative": 0
    },
    {
        "comment": "包子老师的学生集合",
        "user_name": "喜欢折纸的某人",
        "user_sex": "男",
        "like_count": 11,
        "reply_count": 3,
        "comment_date": "2022-07-30 15:13:36",
        "confidence": 0,
        "positive": 0,
        "negative": 0
    },
    {
        "comment": "这个短片被我学校发现了，昨天开班会时放到课件里的，看到安黛因了专门回来搜一下，那时候差点在学校哭出来，简直和我的经历是一模一样，（我六年级）看这个短片时小女孩每上一个枷锁他们就笑，那一刻我感受到了，他们是那么无知[酸了]",
        "user_name": "补钙喝六个硬币",
        "user_sex": "男",
        "like_count": 5,
        "reply_count": 1,
        "comment_date": "2023-02-21 12:59:48",
        "confidence": 0,
        "positive": 0,
        "negative": 0
    },
    {
        "comment": "这是内心的小孩吗",
        "user_name": "w超越自我-",
        "user_sex": "男",
        "like_count": 3,
        "reply_count": 0,
        "comment_date": "2022-10-26 15:31:10",
        "confidence": 0,
        "positive": 0,
        "negative": 0
    },
    {
        "comment": "这种动画真的很棒啊",
        "user_name": "洛M明三",
        "user_sex": "保密",
        "like_count": 2,
        "reply_count": 0,
        "comment_date": "2022-05-24 02:58:34",
        "confidence": 0,
        "positive": 0,
        "negative": 0
    },
    {
        "comment": "真的真的非常非常的棒[打call]，我拿去发个QQ空间咯[脱单doge]",
        "user_name": "青城山下杨瞎子",
        "user_sex": "保密",
        "like_count": 1,
        "reply_count": 0,
        "comment_date": "2022-11-26 19:56:42",
        "confidence": 0,
        "positive": 0,
        "negative": 0
    },
    {
        "comment": "好",
        "user_name": "阿伦老师专注解决社恐",
        "user_sex": "男",
        "like_count": 0,
        "reply_count": 0,
        "comment_date": "2022-02-16 09:14:16",
        "confidence": 0,
        "positive": 0,
        "negative": 0
    },
    {
        "comment": "带我一个",
        "user_name": "黑光不生白影不死",
        "user_sex": "保密",
        "like_count": 0,
        "reply_count": 0,
        "comment_date": "2022-08-19 20:56:56",
        "confidence": 0,
        "positive": 0,
        "negative": 0
    },
    {
        "comment": "小的时候，容易为他人的指责而套上心灵的枷锁；长大以后，却一次次为自己套上沉重的生存枷锁。这则短片提供了一个新的视角——如果再遇见儿时的自己，你愿不愿意去拥抱ta、守护ta？答案是肯定的，因为那个年幼的自己天真而脆弱，却一脉相承、心灵相通。那么，当我们垂垂老矣时，也一定想要全心爱护当下的你。所以，请替你照顾好自己~",
        "user_name": "suger_椰子皮",
        "user_sex": "女",
        "like_count": 0,
        "reply_count": 0,
        "comment_date": "2024-02-23 22:41:01",
        "confidence": 0,
        "positive": 0,
        "negative": 0
    },
    {
        "comment": "每一个人都值得被爱，你真的很棒",
        "user_name": "昵称好长长长长长长长",
        "user_sex": "女",
        "like_count": 0,
        "reply_count": 0,
        "comment_date": "2023-03-21 10:34:23",
        "confidence": 0,
        "positive": 0,
        "negative": 0
    },
    {
        "comment": "永远都是想骂人的状态，改不了了，咋办。",
        "user_name": "战阵冲杀",
        "user_sex": "保密",
        "like_count": 0,
        "reply_count": 1,
        "comment_date": "2023-11-15 06:53:17",
        "confidence": 0,
        "positive": 0,
        "negative": 0
    },
    {
        "comment": "为什么没声音",
        "user_name": "张小小小群",
        "user_sex": "保密",
        "like_count": 0,
        "reply_count": 0,
        "comment_date": "2023-04-17 15:58:00",
        "confidence": 0,
        "positive": 0,
        "negative": 0
    }
]